autogit/__init__.py
autogit/cli.py
autogit/constants.py
autogit/data_types.py
autogit/actions/_1_parse_arguments.py
autogit/actions/_2_get_repository_states.py
autogit/actions/_3_get_tokens_and_api_versions.py
autogit/actions/_4_clone_repositories.py
autogit/actions/_5_create_branch.py
autogit/actions/_6_run_command.py
autogit/actions/_7_commit_and_push_changes.py
autogit/actions/_8_create_pull_request.py
autogit/actions/__init__.py
autogit/utils/__init__.py
autogit/utils/helpers.py
autogit/utils/print.py
autogit/utils/throttled_tasks_executor.py
examples/update_mypy_version.py
experiments/rich_multiline_update_example.py
experiments/rich_progress_bar_example.py
manual_tests/add_hello_to_readme.py
manual_tests/bump_python_version.py
autogit-0.0.42.dist-info/METADATA
autogit-0.0.42.dist-info/WHEEL
autogit-0.0.42.dist-info/entry_points.txt
autogit-0.0.42.dist-info/licenses/LICENSE
autogit-0.0.42.dist-info/RECORD
