Metadata-Version: 2.4
Name: autogit
Version: 0.0.42
Summary: autogit is a command line tool for updating multiple GitLab or GitHub repositories with a single command.
Project-URL: homepage, https://github.com/albertas/autogit
Author-email: Albertas Gimbutas <albertasgim@gmail.com>
License-File: LICENSE
Classifier: Development Status :: 3 - Alpha
Classifier: License :: OSI Approved :: GNU Affero General Public License v3
Classifier: Natural Language :: English
Classifier: Operating System :: OS Independent
Classifier: Programming Language :: Python
Classifier: Programming Language :: Python :: 3.12
Classifier: Programming Language :: Python :: 3.13
Classifier: Programming Language :: Python :: 3.14
Requires-Python: >=3.12
Requires-Dist: gitpython>=3.1.29
Requires-Dist: httpx>=0.23.1
Requires-Dist: rich>=4.0.0
Provides-Extra: test
Requires-Dist: deadcode; extra == 'test'
Requires-Dist: hatch; extra == 'test'
Requires-Dist: mypy; extra == 'test'
Requires-Dist: pip-audit; extra == 'test'
Requires-Dist: pytest; extra == 'test'
Requires-Dist: pytest-asyncio; extra == 'test'
Requires-Dist: pytest-cov; extra == 'test'
Requires-Dist: ruff; extra == 'test'
